{
  "openapi": "3.0.1",
  "info": {
    "title": "HRMS API",
    "description": "API for hrms thesis",
    "contact": {
      "name": "Truong Anh Bao",
      "url": "https://github.com/baotruonganh1230",
      "email": "bao.truonganh1230@hcmut.edu.com"
    },
    "license": {
      "name": "MIT Licence",
      "url": "https://opensource.org/licenses/mit-license.php"
    },
    "version": "2.0"
  },
  "servers": [
    {
      "url": "http://localhost:5000/",
      "description": "Generated server url"
    }
  ],
  "paths": {
    "/api/v1/job/{id}": {
      "get": {
        "tags": [
          "job-controller"
        ],
        "operationId": "getJob",
        "parameters": [
          {
            "name": "id",
            "in": "path",
            "required": true,
            "schema": {
              "type": "integer",
              "format": "int64"
            }
          }
        ],
        "responses": {
          "200": {
            "description": "OK",
            "content": {
              "*/*": {
                "schema": {
                  "type": "object"
                }
              }
            }
          }
        }
      },
      "put": {
        "tags": [
          "job-controller"
        ],
        "operationId": "updateJob",
        "parameters": [
          {
            "name": "id",
            "in": "path",
            "required": true,
            "schema": {
              "type": "integer",
              "format": "int64"
            }
          }
        ],
        "requestBody": {
          "content": {
            "application/json": {
              "schema": {
                "$ref": "#/components/schemas/Job_Recruitment"
              }
            }
          },
          "required": true
        },
        "responses": {
          "200": {
            "description": "OK",
            "content": {
              "*/*": {
                "schema": {
                  "type": "object"
                }
              }
            }
          }
        }
      },
      "post": {
        "tags": [
          "job-controller"
        ],
        "operationId": "insertJob",
        "parameters": [
          {
            "name": "id",
            "in": "path",
            "required": true,
            "schema": {
              "type": "integer",
              "format": "int64"
            }
          }
        ],
        "requestBody": {
          "content": {
            "application/json": {
              "schema": {
                "$ref": "#/components/schemas/Job_Recruitment"
              }
            }
          },
          "required": true
        },
        "responses": {
          "200": {
            "description": "OK",
            "content": {
              "*/*": {
                "schema": {
                  "type": "object"
                }
              }
            }
          }
        }
      }
    },
    "/api/v1/employee/{id}": {
      "get": {
        "tags": [
          "employee-controller"
        ],
        "operationId": "getEmployee",
        "parameters": [
          {
            "name": "id",
            "in": "path",
            "required": true,
            "schema": {
              "type": "integer",
              "format": "int64"
            }
          }
        ],
        "responses": {
          "200": {
            "description": "OK",
            "content": {
              "*/*": {
                "schema": {
                  "type": "object"
                }
              }
            }
          }
        }
      },
      "put": {
        "tags": [
          "employee-controller"
        ],
        "operationId": "updateEmployee",
        "parameters": [
          {
            "name": "id",
            "in": "path",
            "required": true,
            "schema": {
              "type": "integer",
              "format": "int64"
            }
          },
          {
            "name": "data",
            "in": "query",
            "required": true,
            "schema": {
              "type": "string"
            }
          }
        ],
        "requestBody": {
          "content": {
            "application/json": {
              "schema": {
                "required": [
                  "avatar"
                ],
                "type": "object",
                "properties": {
                  "avatar": {
                    "type": "string",
                    "format": "binary"
                  }
                }
              }
            }
          }
        },
        "responses": {
          "200": {
            "description": "OK",
            "content": {
              "*/*": {
                "schema": {
                  "type": "object"
                }
              }
            }
          }
        }
      },
      "post": {
        "tags": [
          "employee-controller"
        ],
        "operationId": "insertEmployee",
        "parameters": [
          {
            "name": "id",
            "in": "path",
            "required": true,
            "schema": {
              "type": "integer",
              "format": "int64"
            }
          },
          {
            "name": "data",
            "in": "query",
            "required": true,
            "schema": {
              "type": "string"
            }
          }
        ],
        "requestBody": {
          "content": {
            "application/json": {
              "schema": {
                "required": [
                  "avatar"
                ],
                "type": "object",
                "properties": {
                  "avatar": {
                    "type": "string",
                    "format": "binary"
                  }
                }
              }
            }
          }
        },
        "responses": {
          "200": {
            "description": "OK",
            "content": {
              "*/*": {
                "schema": {
                  "type": "object"
                }
              }
            }
          }
        }
      }
    },
    "/api/v1/department/{id}": {
      "get": {
        "tags": [
          "department-controller"
        ],
        "operationId": "getDepartment",
        "parameters": [
          {
            "name": "id",
            "in": "path",
            "required": true,
            "schema": {
              "type": "integer",
              "format": "int64"
            }
          }
        ],
        "responses": {
          "200": {
            "description": "OK",
            "content": {
              "*/*": {
                "schema": {
                  "type": "object"
                }
              }
            }
          }
        }
      },
      "put": {
        "tags": [
          "department-controller"
        ],
        "operationId": "updateDepartment",
        "parameters": [
          {
            "name": "id",
            "in": "path",
            "required": true,
            "schema": {
              "type": "integer",
              "format": "int64"
            }
          }
        ],
        "requestBody": {
          "content": {
            "application/json": {
              "schema": {
                "$ref": "#/components/schemas/DepartmentRequest"
              }
            }
          },
          "required": true
        },
        "responses": {
          "200": {
            "description": "OK",
            "content": {
              "*/*": {
                "schema": {
                  "type": "object"
                }
              }
            }
          }
        }
      },
      "post": {
        "tags": [
          "department-controller"
        ],
        "operationId": "insertDepartment",
        "parameters": [
          {
            "name": "id",
            "in": "path",
            "required": true,
            "schema": {
              "type": "integer",
              "format": "int64"
            }
          }
        ],
        "requestBody": {
          "content": {
            "application/json": {
              "schema": {
                "$ref": "#/components/schemas/DepartmentRequest"
              }
            }
          },
          "required": true
        },
        "responses": {
          "200": {
            "description": "OK",
            "content": {
              "*/*": {
                "schema": {
                  "type": "object"
                }
              }
            }
          }
        }
      }
    },
    "/api/v1/account/{eid}/{roleid}": {
      "get": {
        "tags": [
          "account-controller"
        ],
        "operationId": "getAccount",
        "parameters": [
          {
            "name": "eid",
            "in": "path",
            "required": true,
            "schema": {
              "type": "integer",
              "format": "int64"
            }
          },
          {
            "name": "roleid",
            "in": "path",
            "required": true,
            "schema": {
              "type": "integer",
              "format": "int64"
            }
          }
        ],
        "responses": {
          "200": {
            "description": "OK",
            "content": {
              "*/*": {
                "schema": {
                  "type": "object"
                }
              }
            }
          }
        }
      },
      "put": {
        "tags": [
          "account-controller"
        ],
        "operationId": "updateAccount",
        "parameters": [
          {
            "name": "eid",
            "in": "path",
            "required": true,
            "schema": {
              "type": "integer",
              "format": "int64"
            }
          },
          {
            "name": "roleid",
            "in": "path",
            "required": true,
            "schema": {
              "type": "integer",
              "format": "int64"
            }
          }
        ],
        "requestBody": {
          "content": {
            "application/json": {
              "schema": {
                "$ref": "#/components/schemas/Account"
              }
            }
          },
          "required": true
        },
        "responses": {
          "200": {
            "description": "OK",
            "content": {
              "*/*": {
                "schema": {
                  "type": "object"
                }
              }
            }
          }
        }
      },
      "post": {
        "tags": [
          "account-controller"
        ],
        "operationId": "insertAccount",
        "parameters": [
          {
            "name": "eid",
            "in": "path",
            "required": true,
            "schema": {
              "type": "integer",
              "format": "int64"
            }
          },
          {
            "name": "roleid",
            "in": "path",
            "required": true,
            "schema": {
              "type": "integer",
              "format": "int64"
            }
          }
        ],
        "requestBody": {
          "content": {
            "application/json": {
              "schema": {
                "$ref": "#/components/schemas/Account"
              }
            }
          },
          "required": true
        },
        "responses": {
          "200": {
            "description": "OK",
            "content": {
              "*/*": {
                "schema": {
                  "type": "object"
                }
              }
            }
          }
        }
      }
    },
    "/api/v1/registration": {
      "post": {
        "tags": [
          "registration-controller"
        ],
        "operationId": "register",
        "requestBody": {
          "content": {
            "application/json": {
              "schema": {
                "$ref": "#/components/schemas/RegistrationRequest"
              }
            }
          },
          "required": true
        },
        "responses": {
          "200": {
            "description": "OK",
            "content": {
              "*/*": {
                "schema": {
                  "type": "string"
                }
              }
            }
          }
        }
      }
    },
    "/api/v1/auth/login": {
      "post": {
        "tags": [
          "authentication-controller"
        ],
        "operationId": "login",
        "requestBody": {
          "content": {
            "application/json": {
              "schema": {
                "$ref": "#/components/schemas/AuthenticationRequest"
              }
            }
          },
          "required": true
        },
        "responses": {
          "200": {
            "description": "OK",
            "content": {
              "*/*": {
                "schema": {
                  "type": "object"
                }
              }
            }
          }
        }
      }
    },
    "/api/v1/upload": {
      "get": {
        "tags": [
          "employee-controller"
        ],
        "operationId": "uploadFile",
        "responses": {
          "200": {
            "description": "OK",
            "content": {
              "*/*": {
                "schema": {
                  "type": "string"
                }
              }
            }
          }
        }
      }
    },
    "/api/v1/registration/confirm": {
      "get": {
        "tags": [
          "registration-controller"
        ],
        "operationId": "confirm",
        "parameters": [
          {
            "name": "token",
            "in": "query",
            "required": true,
            "schema": {
              "type": "string"
            }
          }
        ],
        "responses": {
          "200": {
            "description": "OK",
            "content": {
              "*/*": {
                "schema": {
                  "type": "string"
                }
              }
            }
          }
        }
      }
    },
    "/api/v1/jobs": {
      "get": {
        "tags": [
          "job-controller"
        ],
        "operationId": "getJobs",
        "responses": {
          "200": {
            "description": "OK",
            "content": {
              "*/*": {
                "schema": {
                  "type": "object"
                }
              }
            }
          }
        }
      }
    },
    "/api/v1/employees": {
      "get": {
        "tags": [
          "employee-controller"
        ],
        "operationId": "getEmployees",
        "responses": {
          "200": {
            "description": "OK",
            "content": {
              "*/*": {
                "schema": {
                  "type": "object"
                }
              }
            }
          }
        }
      }
    },
    "/api/v1/departments": {
      "get": {
        "tags": [
          "department-controller"
        ],
        "operationId": "getDepartments",
        "parameters": [
          {
            "name": "nested",
            "in": "query",
            "required": true,
            "schema": {
              "type": "boolean"
            }
          }
        ],
        "responses": {
          "200": {
            "description": "OK",
            "content": {
              "*/*": {
                "schema": {
                  "type": "object"
                }
              }
            }
          }
        }
      }
    },
    "/api/v1/accounts": {
      "get": {
        "tags": [
          "account-controller"
        ],
        "operationId": "getAccounts",
        "responses": {
          "200": {
            "description": "OK",
            "content": {
              "*/*": {
                "schema": {
                  "type": "object"
                }
              }
            }
          }
        }
      }
    }
  },
  "components": {
    "schemas": {
      "Attendance": {
        "type": "object",
        "properties": {
          "eid": {
            "type": "integer",
            "format": "int64"
          },
          "employee": {
            "$ref": "#/components/schemas/Employee"
          },
          "day": {
            "type": "string",
            "format": "date"
          },
          "time_in": {
            "$ref": "#/components/schemas/LocalTime"
          },
          "time_out": {
            "$ref": "#/components/schemas/LocalTime"
          },
          "deviceId": {
            "type": "string"
          }
        }
      },
      "Bonus_List": {
        "type": "object",
        "properties": {
          "id": {
            "type": "integer",
            "format": "int64"
          },
          "name": {
            "type": "string"
          },
          "amount": {
            "type": "number"
          },
          "employee": {
            "$ref": "#/components/schemas/Employee"
          }
        }
      },
      "Candidate": {
        "type": "object",
        "properties": {
          "id": {
            "type": "integer",
            "format": "int64"
          },
          "name": {
            "type": "string"
          },
          "candidate_cv": {
            "$ref": "#/components/schemas/Candidate_CV"
          },
          "email": {
            "type": "string"
          },
          "job_recruitments": {
            "uniqueItems": true,
            "type": "array",
            "items": {
              "$ref": "#/components/schemas/Job_Recruitment"
            }
          }
        }
      },
      "Candidate_CV": {
        "type": "object",
        "properties": {
          "id": {
            "type": "integer",
            "format": "int64"
          },
          "cv_file_name": {
            "type": "string"
          },
          "cv_file_type": {
            "type": "string"
          },
          "cv_file_size": {
            "type": "integer",
            "format": "int64"
          },
          "cv_file_content": {
            "type": "array",
            "items": {
              "type": "string",
              "format": "byte"
            }
          },
          "candidate": {
            "$ref": "#/components/schemas/Candidate"
          }
        }
      },
      "Department": {
        "type": "object",
        "properties": {
          "id": {
            "type": "integer",
            "format": "int64"
          },
          "location": {
            "type": "string"
          },
          "name": {
            "type": "string"
          },
          "peopleNumber": {
            "type": "integer",
            "format": "int32"
          },
          "type": {
            "type": "string"
          },
          "description": {
            "type": "string"
          },
          "subUnits": {
            "uniqueItems": true,
            "type": "array",
            "items": {
              "$ref": "#/components/schemas/Department"
            }
          },
          "headOfUnit": {
            "$ref": "#/components/schemas/Department"
          },
          "manage": {
            "$ref": "#/components/schemas/Manage"
          },
          "works_ins": {
            "type": "array",
            "items": {
              "$ref": "#/components/schemas/Works_In"
            }
          }
        }
      },
      "Employee": {
        "type": "object",
        "properties": {
          "id": {
            "type": "integer",
            "format": "int64"
          },
          "first_name": {
            "type": "string"
          },
          "last_name": {
            "type": "string"
          },
          "email": {
            "type": "string"
          },
          "permanent_address": {
            "type": "string"
          },
          "temporary_address": {
            "type": "string"
          },
          "phone": {
            "type": "string"
          },
          "gross_salary": {
            "type": "number"
          },
          "employed_date": {
            "type": "string",
            "format": "date"
          },
          "sex": {
            "type": "string"
          },
          "date_of_birth": {
            "type": "string",
            "format": "date"
          },
          "pit": {
            "type": "string"
          },
          "avatar": {
            "type": "string"
          },
          "attendances": {
            "type": "array",
            "items": {
              "$ref": "#/components/schemas/Attendance"
            }
          },
          "payments": {
            "type": "array",
            "items": {
              "$ref": "#/components/schemas/Payment"
            }
          },
          "leaves": {
            "type": "array",
            "items": {
              "$ref": "#/components/schemas/Leaves"
            }
          },
          "position": {
            "$ref": "#/components/schemas/Position"
          },
          "manage": {
            "$ref": "#/components/schemas/Manage"
          },
          "managed_by": {
            "$ref": "#/components/schemas/Managed_By"
          },
          "insurances": {
            "type": "array",
            "items": {
              "$ref": "#/components/schemas/Insurance"
            }
          },
          "tasks": {
            "uniqueItems": true,
            "type": "array",
            "items": {
              "$ref": "#/components/schemas/Task"
            }
          },
          "works_in": {
            "$ref": "#/components/schemas/Works_In"
          },
          "works_on": {
            "$ref": "#/components/schemas/Works_On"
          },
          "bonus_lists": {
            "type": "array",
            "items": {
              "$ref": "#/components/schemas/Bonus_List"
            }
          }
        }
      },
      "Has": {
        "type": "object",
        "properties": {
          "position": {
            "$ref": "#/components/schemas/Position"
          },
          "job_recruitment": {
            "$ref": "#/components/schemas/Job_Recruitment"
          }
        }
      },
      "Insurance": {
        "type": "object",
        "properties": {
          "id": {
            "type": "integer",
            "format": "int64"
          },
          "eid": {
            "type": "integer",
            "format": "int64"
          },
          "typeid": {
            "type": "integer",
            "format": "int64"
          },
          "employee": {
            "$ref": "#/components/schemas/Employee"
          },
          "type": {
            "$ref": "#/components/schemas/Insurance_Type"
          },
          "from_date": {
            "type": "string",
            "format": "date"
          },
          "to_date": {
            "type": "string",
            "format": "date"
          },
          "issue_date": {
            "type": "string",
            "format": "date"
          },
          "number": {
            "type": "string"
          },
          "cityId": {
            "type": "integer",
            "format": "int64"
          },
          "kcbId": {
            "type": "integer",
            "format": "int64"
          }
        }
      },
      "Insurance_Type": {
        "type": "object",
        "properties": {
          "id": {
            "type": "integer",
            "format": "int64"
          },
          "name": {
            "type": "string"
          },
          "rate_of_payment": {
            "type": "number"
          },
          "insurances": {
            "type": "array",
            "items": {
              "$ref": "#/components/schemas/Insurance"
            }
          }
        }
      },
      "Job_Recruitment": {
        "type": "object",
        "properties": {
          "id": {
            "type": "integer",
            "format": "int64"
          },
          "title": {
            "type": "string"
          },
          "job_description": {
            "type": "string"
          },
          "note": {
            "type": "string"
          },
          "from_date": {
            "type": "string",
            "format": "date"
          },
          "to_date": {
            "type": "string",
            "format": "date"
          },
          "status": {
            "type": "integer",
            "format": "int32"
          },
          "has": {
            "$ref": "#/components/schemas/Has"
          },
          "candidates": {
            "uniqueItems": true,
            "type": "array",
            "items": {
              "$ref": "#/components/schemas/Candidate"
            }
          }
        }
      },
      "Leave_Type": {
        "type": "object",
        "properties": {
          "id": {
            "type": "integer",
            "format": "int64"
          },
          "name": {
            "type": "string"
          },
          "is_paid": {
            "type": "boolean"
          },
          "leaves": {
            "type": "array",
            "items": {
              "$ref": "#/components/schemas/Leaves"
            }
          }
        }
      },
      "Leaves": {
        "type": "object",
        "properties": {
          "eid": {
            "type": "integer",
            "format": "int64"
          },
          "typeid": {
            "type": "integer",
            "format": "int64"
          },
          "employee": {
            "$ref": "#/components/schemas/Employee"
          },
          "type": {
            "$ref": "#/components/schemas/Leave_Type"
          },
          "from_date": {
            "type": "string",
            "format": "date"
          },
          "to_date": {
            "type": "string",
            "format": "date"
          },
          "description": {
            "type": "string"
          }
        }
      },
      "LocalTime": {
        "type": "object",
        "properties": {
          "hour": {
            "type": "integer",
            "format": "int32"
          },
          "minute": {
            "type": "integer",
            "format": "int32"
          },
          "second": {
            "type": "integer",
            "format": "int32"
          },
          "nano": {
            "type": "integer",
            "format": "int32"
          }
        }
      },
      "Manage": {
        "type": "object",
        "properties": {
          "department": {
            "$ref": "#/components/schemas/Department"
          },
          "employee": {
            "$ref": "#/components/schemas/Employee"
          }
        }
      },
      "Managed_By": {
        "type": "object",
        "properties": {
          "employee": {
            "$ref": "#/components/schemas/Employee"
          },
          "project": {
            "$ref": "#/components/schemas/Project"
          }
        }
      },
      "Payment": {
        "type": "object",
        "properties": {
          "eid": {
            "type": "integer",
            "format": "int64"
          },
          "employee": {
            "$ref": "#/components/schemas/Employee"
          },
          "personal_tax": {
            "type": "number"
          },
          "derived_salary": {
            "type": "number"
          },
          "payment_date": {
            "type": "string",
            "format": "date"
          },
          "other_income": {
            "type": "number"
          },
          "mandatory_insurance": {
            "type": "number"
          },
          "payroll": {
            "$ref": "#/components/schemas/Payroll"
          }
        }
      },
      "Payroll": {
        "type": "object",
        "properties": {
          "id": {
            "type": "integer",
            "format": "int64"
          },
          "name": {
            "type": "string"
          },
          "created_time": {
            "type": "string",
            "format": "date"
          }
        }
      },
      "Position": {
        "type": "object",
        "properties": {
          "id": {
            "type": "integer",
            "format": "int64"
          },
          "name": {
            "type": "string"
          },
          "min_salary": {
            "type": "number"
          },
          "max_salary": {
            "type": "number"
          },
          "salaryGroup": {
            "type": "integer",
            "format": "int32"
          },
          "description": {
            "type": "string"
          },
          "has": {
            "$ref": "#/components/schemas/Has"
          },
          "employees": {
            "type": "array",
            "items": {
              "$ref": "#/components/schemas/Employee"
            }
          }
        }
      },
      "Project": {
        "type": "object",
        "properties": {
          "id": {
            "type": "integer",
            "format": "int64"
          },
          "name": {
            "type": "string"
          },
          "start_date": {
            "type": "string",
            "format": "date"
          },
          "end_date": {
            "type": "string",
            "format": "date"
          },
          "managed_by": {
            "$ref": "#/components/schemas/Managed_By"
          },
          "tasks": {
            "type": "array",
            "items": {
              "$ref": "#/components/schemas/Task"
            }
          },
          "works_ons": {
            "type": "array",
            "items": {
              "$ref": "#/components/schemas/Works_On"
            }
          }
        }
      },
      "Task": {
        "type": "object",
        "properties": {
          "id": {
            "type": "integer",
            "format": "int64"
          },
          "pid": {
            "type": "integer",
            "format": "int64"
          },
          "status": {
            "type": "string"
          },
          "title": {
            "type": "string"
          },
          "content": {
            "type": "string"
          },
          "project": {
            "$ref": "#/components/schemas/Project"
          },
          "employees": {
            "uniqueItems": true,
            "type": "array",
            "items": {
              "$ref": "#/components/schemas/Employee"
            }
          }
        }
      },
      "Works_In": {
        "type": "object",
        "properties": {
          "eid": {
            "type": "integer",
            "format": "int64"
          },
          "employee": {
            "$ref": "#/components/schemas/Employee"
          },
          "department": {
            "$ref": "#/components/schemas/Department"
          }
        }
      },
      "Works_On": {
        "type": "object",
        "properties": {
          "employee": {
            "$ref": "#/components/schemas/Employee"
          },
          "project": {
            "$ref": "#/components/schemas/Project"
          },
          "hours": {
            "type": "integer",
            "format": "int64"
          }
        }
      },
      "DepartmentRequest": {
        "type": "object",
        "properties": {
          "id": {
            "type": "integer",
            "format": "int64"
          },
          "location": {
            "type": "string"
          },
          "name": {
            "type": "string"
          },
          "peopleNumber": {
            "type": "integer",
            "format": "int32"
          },
          "type": {
            "type": "string"
          },
          "description": {
            "type": "string"
          },
          "headOfUnitId": {
            "type": "integer",
            "format": "int64"
          },
          "subUnits": {
            "uniqueItems": true,
            "type": "array",
            "items": {
              "$ref": "#/components/schemas/DepartmentRequest"
            }
          }
        }
      },
      "Account": {
        "type": "object",
        "properties": {
          "eid": {
            "type": "integer",
            "format": "int64"
          },
          "roleid": {
            "type": "integer",
            "format": "int64"
          },
          "employee": {
            "$ref": "#/components/schemas/Employee"
          },
          "role": {
            "$ref": "#/components/schemas/Role"
          },
          "username": {
            "type": "string"
          },
          "password": {
            "type": "string"
          },
          "status": {
            "type": "string",
            "enum": [
              "enable",
              "disable"
            ]
          },
          "enabled": {
            "type": "boolean"
          },
          "authorities": {
            "type": "array",
            "items": {
              "$ref": "#/components/schemas/GrantedAuthority"
            }
          },
          "accountNonLocked": {
            "type": "boolean"
          },
          "accountNonExpired": {
            "type": "boolean"
          },
          "credentialsNonExpired": {
            "type": "boolean"
          }
        }
      },
      "GrantedAuthority": {
        "type": "object",
        "properties": {
          "authority": {
            "type": "string"
          }
        }
      },
      "Role": {
        "type": "object",
        "properties": {
          "id": {
            "type": "integer",
            "format": "int64"
          },
          "name": {
            "type": "string"
          },
          "description": {
            "type": "string"
          },
          "authority": {
            "type": "string"
          }
        }
      },
      "RegistrationRequest": {
        "type": "object",
        "properties": {
          "first_name": {
            "type": "string"
          },
          "last_name": {
            "type": "string"
          },
          "email": {
            "type": "string"
          },
          "phone": {
            "type": "string"
          },
          "sex": {
            "type": "string"
          },
          "date_of_birth": {
            "type": "string"
          },
          "username": {
            "type": "string"
          },
          "password": {
            "type": "string"
          },
          "permanent_address": {
            "type": "string"
          },
          "temporary_address": {
            "type": "string"
          }
        }
      },
      "AuthenticationRequest": {
        "type": "object",
        "properties": {
          "username": {
            "type": "string"
          },
          "password": {
            "type": "string"
          }
        }
      }
    }
  }
}